keep/api/__init__.py
keep/api/api.py
keep/api/core/config.py
keep/api/core/db.py
keep/api/core/dependencies.py
keep/api/logging.py
keep/api/models/__init__.py
keep/api/models/alert.py
keep/api/models/db/alert.py
keep/api/models/db/provider.py
keep/api/models/db/tenant.py
keep/api/models/db/user.py
keep/api/models/db/workflow.py
keep/api/models/provider.py
keep/api/models/smtp.py
keep/api/models/step_context.py
keep/api/models/user.py
keep/api/models/webhook.py
keep/api/models/workflow.py
keep/api/observability.py
keep/api/routes/__init__.py
keep/api/routes/ai.py
keep/api/routes/alerts.py
keep/api/routes/healthcheck.py
keep/api/routes/providers.py
keep/api/routes/pusher.py
keep/api/routes/settings.py
keep/api/routes/status.py
keep/api/routes/tenant.py
keep/api/routes/whoami.py
keep/api/routes/workflows.py
keep/api/utils/auth0_utils.py
keep/api/utils/gpt_utils.py
keep/api/utils/tenant_utils.py
keep/cli/cli.py
keep/cli/click_extensions.py
keep/conditions/__init__.py
keep/conditions/assert_condition.py
keep/conditions/base_condition.py
keep/conditions/condition_factory.py
keep/conditions/stddev_condition.py
keep/conditions/threshold_condition.py
keep/contextmanager/__init__.py
keep/contextmanager/contextmanager.py
keep/event_subscriber/__init__.py
keep/event_subscriber/event_subscriber.py
keep/exceptions/__init__.py
keep/exceptions/action_error.py
keep/exceptions/provider_config_exception.py
keep/exceptions/provider_connection_failed.py
keep/exceptions/provider_exception.py
keep/functions/__init__.py
keep/iohandler/iohandler.py
keep/parser/parser.py
keep/posthog/posthog.py
keep/providers/__init__.py
keep/providers/aks_provider/aks_provider.py
keep/providers/auth0_provider/__init__.py
keep/providers/auth0_provider/auth0_provider.py
keep/providers/axiom_provider/__init__.py
keep/providers/axiom_provider/axiom_provider.py
keep/providers/base/__init__.py
keep/providers/base/base_provider.py
keep/providers/base/provider_exceptions.py
keep/providers/bash_provider/__init__.py
keephq-0.2.7.dist-info/LICENSE
keephq-0.2.7.dist-info/METADATA
keephq-0.2.7.dist-info/WHEEL
keephq-0.2.7.dist-info/entry_points.txt
keephq-0.2.7.dist-info/RECORD
