Metadata-Version: 2.1
Name: keephq
Version: 0.2.7
Summary: Alerting. for developers, by developers.
Author: Keep Alerting LTD
Requires-Python: >=3.11,<3.12
Classifier: Programming Language :: Python :: 3
Classifier: Programming Language :: Python :: 3.11
Requires-Dist: asteval (>=0.9.31,<0.10.0)
Requires-Dist: astunparse (>=1.6.3,<2.0.0)
Requires-Dist: asyncio (>=3.4.3,<4.0.0)
Requires-Dist: auth0-python (>=4.4.1,<5.0.0)
Requires-Dist: azure-identity (>=1.15.0,<2.0.0)
Requires-Dist: azure-mgmt-containerservice (>=27.0.0,<28.0.0)
Requires-Dist: boto3 (>=1.26.72,<2.0.0)
Requires-Dist: chevron (>=0.14.0,<0.15.0)
Requires-Dist: click (>=8.1.3,<9.0.0)
Requires-Dist: cloud-sql-python-connector (>=1.2.3,<2.0.0)
Requires-Dist: datadog-api-client (>=2.12.0,<3.0.0)
Requires-Dist: datefinder (>=0.7.3,<0.8.0)
Requires-Dist: elasticsearch (>=8.6.1,<9.0.0)
Requires-Dist: fastapi (>=0.92.0,<0.93.0)
Requires-Dist: google-cloud-bigquery (>=3.11.0,<4.0.0)
Requires-Dist: google-cloud-container (>=2.32.0,<3.0.0)
Requires-Dist: google-cloud-secret-manager (>=2.16.1,<3.0.0)
Requires-Dist: google-cloud-storage (>=2.10.0,<3.0.0)
Requires-Dist: grafana-api-sdk (>=0.1.0,<0.2.0)
Requires-Dist: jwcrypto (>=1.4.2,<2.0.0)
Requires-Dist: kafka-python (>=2.0.2,<3.0.0)
Requires-Dist: kubernetes (>=27.2.0,<28.0.0)
Requires-Dist: langchain (>=0.0.329,<0.0.330)
Requires-Dist: logmine (>=0.4.1,<0.5.0)
Requires-Dist: mysql-connector-python (>=8.0.32,<9.0.0)
Requires-Dist: nest-asyncio (>=1.5.6,<2.0.0)
Requires-Dist: openai (>=0.27.7,<0.28.0)
Requires-Dist: opentelemetry-exporter-gcp-trace (>=1.6.0,<2.0.0)
Requires-Dist: opentelemetry-exporter-otlp-proto-grpc (>=1.20.0,<2.0.0)
Requires-Dist: opentelemetry-exporter-otlp-proto-http (>=1.20.0,<2.0.0)
Requires-Dist: opentelemetry-instrumentation-fastapi (>=0.41b0,<0.42)
Requires-Dist: opentelemetry-instrumentation-logging (>=0.41b0,<0.42)
Requires-Dist: opentelemetry-instrumentation-requests (>=0.41b0,<0.42)
Requires-Dist: opentelemetry-instrumentation-sqlalchemy (>=0.41b0,<0.42)
Requires-Dist: opentelemetry-propagator-gcp (>=1.5.0,<2.0.0)
Requires-Dist: opentelemetry-sdk (>=1.20.0,<2.0.0)
Requires-Dist: opsgenie-sdk (>=2.1.5,<3.0.0)
Requires-Dist: paramiko (>=3.0.0,<4.0.0)
Requires-Dist: posthog (>=3.0.1,<4.0.0)
Requires-Dist: prettytable (>=3.9.0,<4.0.0)
Requires-Dist: psycopg2-binary (>=2.9.5,<3.0.0)
Requires-Dist: pusher (>=3.3.2,<4.0.0)
Requires-Dist: pydantic (>=1.10.4,<2.0.0)
Requires-Dist: pygithub (>=1.57,<2.0)
Requires-Dist: pympler (>=1.0.1,<2.0.0)
Requires-Dist: pymysql (>=1.0.3,<2.0.0)
Requires-Dist: pyngrok (>=6.0.0,<7.0.0)
Requires-Dist: python-dotenv (>=0.21.1,<0.22.0)
Requires-Dist: python-jose (>=3.3.0,<4.0.0)
Requires-Dist: python-json-logger (>=2.0.6,<3.0.0)
Requires-Dist: python-multipart (>=0.0.6,<0.0.7)
Requires-Dist: python-telegram-bot (>=20.1,<21.0)
Requires-Dist: pyyaml (>=6.0,<7.0)
Requires-Dist: requests (>=2.28.2,<3.0.0)
Requires-Dist: sentry-sdk (>=1.15.0,<2.0.0)
Requires-Dist: snowflake-connector-python (==3.1.0)
Requires-Dist: sqlalchemy (==1.4.41)
Requires-Dist: sqlmodel (>=0.0.8,<0.0.9)
Requires-Dist: starlette-context (>=0.3.6,<0.4.0)
Requires-Dist: twilio (>=8.10.0,<9.0.0)
Requires-Dist: uvicorn (>=0.20.0,<0.21.0)
Requires-Dist: validators (>=0.20.0,<0.21.0)
Requires-Dist: websocket-client (>=1.6.0,<2.0.0)
